julan_nasser/__init__.py
julan_nasser/corrector.py
julan_nasser/dataset_creator.py
julan_nasser/io_handler.py
julan_nasser/preprocess.py
julan_nasser/proj_config.py
julan_nasser/string_manipulator.py
julan_nasser/models/__init__.py
julan_nasser/models/base_model.py
julan_nasser/models/markov_model.py
julan_nasser/models/n_gram.py
julan_nasser/models/vocabs_creator.py
julan_nasser/resources/big.txt
julan_nasser/resources/close_vocabs.pickle
julan_nasser/resources/ngram.pickle
julan_nasser/resources/ngram_plus1.pickle
julan_nasser/resources/vocab_freqs.pickle
julan_nasser-0.0.3.dist-info/LICENSE
julan_nasser-0.0.3.dist-info/METADATA
julan_nasser-0.0.3.dist-info/WHEEL
julan_nasser-0.0.3.dist-info/top_level.txt
julan_nasser-0.0.3.dist-info/RECORD
