Metadata-Version: 2.1
Name: julan-nasser
Version: 0.0.3
Summary: Arabic Spell Checker And Corrector Using NLP
Home-page: UNKNOWN
Author: Julan_Nasser
Author-email: Julan-Nasser@gmail.com
License: UNKNOWN
Keywords: nlp,ar-nlp,nlp-ar,ar spell check,ar spell corrector
Platform: UNKNOWN
Classifier: Development Status :: 1 - Planning
Classifier: Intended Audience :: Developers
Classifier: Programming Language :: Python :: 3
Classifier: Operating System :: Unix
Classifier: Operating System :: MacOS :: MacOS X
Classifier: Operating System :: Microsoft :: Windows
License-File: LICENSE
